Metadata-Version: 1.1
Name: pycatalog
Version: 1.2.0
Summary: Data structure for complexe enumeration.
Home-page: https://github.com/jsatt/python-catalog
Author: Jeremy Satterfield
Author-email: jsatt@jsatt.com
License: MIT License
Platform: UNKNOWN
Classifier: Development Status :: 4 - Beta
Classifier: Environment :: Console
Classifier: Intended Audience :: Developers
Classifier: License :: OSI Approved :: MIT License
Classifier: Natural Language :: English
Classifier: Operating System :: OS Independent
Classifier: Programming Language :: Python :: 2
Classifier: Programming Language :: Python :: 3
Classifier: Topic :: Software Development
